abdulqader_calculator_package/__init__.py
abdulqader_calculator_package/calculator.py
simple_calculator_abdulqader_alalfi-0.1.0.dist-info/licenses/LICENSE
simple_calculator_abdulqader_alalfi-0.1.0.dist-info/METADATA
simple_calculator_abdulqader_alalfi-0.1.0.dist-info/WHEEL
simple_calculator_abdulqader_alalfi-0.1.0.dist-info/top_level.txt
simple_calculator_abdulqader_alalfi-0.1.0.dist-info/RECORD
